mclibre_python_testing_client/__init__.py
mclibre_python_testing_client/__main__.py
mclibre_python_testing_client/mptc.py
mclibre_python_testing_client-0.0.47.dist-info/LICENSE
mclibre_python_testing_client-0.0.47.dist-info/METADATA
mclibre_python_testing_client-0.0.47.dist-info/WHEEL
mclibre_python_testing_client-0.0.47.dist-info/entry_points.txt
mclibre_python_testing_client-0.0.47.dist-info/top_level.txt
mclibre_python_testing_client-0.0.47.dist-info/RECORD
