Metadata-Version: 2.1
Name: mclibre_python_testing_client
Version: 0.0.47
Summary: Testing tool for some of the exercises in mclibre.org's Python course available at https://www.mclibre.org/consultar/python/
Home-page: https://github.com/BartolomeSintes/mclibre-python-testing/
Author: Bartolome Sintes
Author-email: bartolome.sintes@gmail.com
Classifier: Programming Language :: Python :: 3
Classifier: License :: OSI Approved :: GNU Affero General Public License v3 or later (AGPLv3+)
Classifier: Operating System :: OS Independent
License-File: LICENSE
Requires-Dist: requests
Requires-Dist: pytest
